basicthainlp/__init__.py
basicthainlp/findSimilarityTerms/__init__.py
basicthainlp/findSimilarityTerms/find_similarity_terms.py
basicthainlp/findSimilarityTerms/input/dict_en.txt
basicthainlp/findSimilarityTerms/input/dict_th.txt
basicthainlp/pmSeg/PmSeg.py
basicthainlp/pmSeg/__init__.py
basicthainlp/pmSeg/input/thaiSylseg.def
basicthainlp/pmSeg/output/.DS_Store
basicthainlp/pmSeg/output/pm_crf.model
basicthainlp/posTag/PosTag.py
basicthainlp/posTag/__init__.py
basicthainlp/posTag/output/pos_crf.model
basicthainlp/spelling/Spelling.py
basicthainlp/spelling/__init__.py
basicthainlp/spelling/input/dict_lexitron.txt
basicthainlp/tokenIdentification/TokenIden.py
basicthainlp/tokenIdentification/__init__.py
basicthainlp-0.5.8.dist-info/LICENSE.txt
basicthainlp-0.5.8.dist-info/METADATA
basicthainlp-0.5.8.dist-info/WHEEL
basicthainlp-0.5.8.dist-info/top_level.txt
basicthainlp-0.5.8.dist-info/RECORD
