Metadata-Version: 2.1
Name: basicthainlp
Version: 0.5.8
Summary: Basic nlp for thai
Home-page: 
Author: bablueza
Author-email: bablueza@gmail.com
License: MIT
Requires-Python: >=3.8
License-File: LICENSE.txt
Requires-Dist: numpy
Requires-Dist: sklearn-crfsuite
Requires-Dist: langdetect
